app_gradio/__init__.py
app_gradio/demo_gradio.py
app_gradio/gradio_i18n.json
config/__init__.py
config/config.yaml.example
config/config_run.yaml.example
webqa_agent/__init__.py
webqa_agent/cli.py
webqa_agent/actions/__init__.py
webqa_agent/actions/action_executor.py
webqa_agent/actions/action_handler.py
webqa_agent/actions/action_types.py
webqa_agent/actions/click_handler.py
webqa_agent/actions/scroll_handler.py
webqa_agent/browser/__init__.py
webqa_agent/browser/check.py
webqa_agent/browser/config.py
webqa_agent/browser/session.py
webqa_agent/crawler/__init__.py
webqa_agent/crawler/crawl.py
webqa_agent/crawler/deep_crawler.py
webqa_agent/crawler/dom_cacher.py
webqa_agent/crawler/dom_tree.py
webqa_agent/crawler/feature_detector.py
webqa_agent/crawler/js/element_detector.js
webqa_agent/crawler/js/marker_remover.js
webqa_agent/crawler/js/text_extractor.js
webqa_agent/data/__init__.py
webqa_agent/data/case_structures.py
webqa_agent/data/test_structures.py
webqa_agent/executor/__init__.py
webqa_agent/executor/case_executor.py
webqa_agent/executor/case_mode.py
webqa_agent/executor/parallel_executor.py
webqa_agent/executor/parallel_mode.py
webqa_agent/executor/result_aggregator.py
webqa_agent/executor/test_runners.py
webqa_agent/llm/llm_api.py
webqa_agent/llm/prompt.py
webqa_agent/static/index.html
webqa_agent/static/template.html
webqa_agent/static/vite.svg
webqa_agent/static/assets/index.js
webqa_agent/static/assets/index_en-US.js
webqa_agent/static/assets/style.css
webqa_agent/static/i18n/en-US.json
webqa_agent/static/i18n/zh-CN.json
webqa_agent/testers/__init__.py
webqa_agent/testers/basic_tester.py
webqa_agent/testers/function_tester.py
webqa_agent/testers/performance_tester.py
webqa_agent/testers/ux_tester.py
webqa_agent/testers/case_gen/__init__.py
webqa_agent/testers/case_gen/graph.py
webqa_agent/testers/case_gen/agents/__init__.py
webqa_agent/testers/case_gen/agents/execute_agent.py
webqa_agent/testers/case_gen/prompts/__init__.py
webqa_agent-0.2.2.post1.dist-info/licenses/LICENSE
webqa_agent-0.2.2.post1.dist-info/METADATA
webqa_agent-0.2.2.post1.dist-info/WHEEL
webqa_agent-0.2.2.post1.dist-info/entry_points.txt
webqa_agent-0.2.2.post1.dist-info/top_level.txt
webqa_agent-0.2.2.post1.dist-info/RECORD
