Metadata-Version: 2.4
Name: webqa-agent
Version: 0.2.2.post1
Summary: WebQA Agent is an autonomous web browser agent that audits performance, functionality & UX for engineers and vibe-coding creators.
Author: MigoXLab
License-Expression: Apache-2.0
Project-URL: Homepage, https://github.com/MigoXLab/webqa-agent
Project-URL: Repository, https://github.com/MigoXLab/webqa-agent
Project-URL: Documentation, https://github.com/MigoXLab/webqa-agent#readme
Project-URL: Issues, https://github.com/MigoXLab/webqa-agent/issues
Keywords: web,qa,testing,automation,playwright,ai
Classifier: Development Status :: 4 - Beta
Classifier: Intended Audience :: Developers
Classifier: Programming Language :: Python :: 3
Classifier: Programming Language :: Python :: 3.11
Classifier: Programming Language :: Python :: 3.12
Classifier: Topic :: Software Development :: Testing
Classifier: Topic :: Internet :: WWW/HTTP :: Browsers
Requires-Python: >=3.11
License-File: LICENSE
Requires-Dist: anthropic>=0.40.0
Requires-Dist: html2text>=2025.4.15
Requires-Dist: jinja2>=3.1.6
Requires-Dist: langchain==0.3.26
Requires-Dist: langchain-anthropic==0.3.17
Requires-Dist: langchain-core==0.3.68
Requires-Dist: langchain-openai==0.3.27
Requires-Dist: langgraph==0.5.1
Requires-Dist: langgraph-checkpoint==2.1.0
Requires-Dist: openai>=1.93.0
Requires-Dist: pillow==11.3.0
Requires-Dist: playwright==1.52.0
Requires-Dist: pre-commit>=4.5.1
Requires-Dist: pydantic==2.9.2
Requires-Dist: pytest>=8.4.1
Requires-Dist: pytest-asyncio>=1.3.0
Requires-Dist: python-dotenv>=1.1.1
Requires-Dist: pyyaml>=6.0.2
Requires-Dist: requests>=2.32.4
Requires-Dist: typing-extensions==4.14.0
Dynamic: license-file
